Workbook

Sheet Summary
A1: S&P 500 Membership History by Two-Year Period
A3: Period | B3: Snapshot date (start) | C3: Members at start | D3: Added in period | E3: Removed in period | F3: Members at end | G3: Check vs next snapshot
A4: 1996 - 1997 | B4: 1996-01-02 | C4: =COUNT(Membership_Snapshots!D2:D1193) | D4: =COUNTIFS(Changes_Log!$B$2:$B$1535,A4,Changes_Log!$E$2:$E$1535,"Added") | E4: =COUNTIFS(Changes_Log!$B$2:$B$1535,A4,Changes_Log!$E$2:$E$1535,"Removed") | F4: =C4+D4-E4 | G4: =IF(F4=C5,"OK","MISMATCH")
A5: 1998 - 1999 | B5: 1998-01-01 | C5: =COUNT(Membership_Snapshots!E2:E1193) | D5: =COUNTIFS(Changes_Log!$B$2:$B$1535,A5,Changes_Log!$E$2:$E$1535,"Added") | E5: =COUNTIFS(Changes_Log!$B$2:$B$1535,A5,Changes_Log!$E$2:$E$1535,"Removed") | F5: =C5+D5-E5 | G5: =IF(F5=C6,"OK","MISMATCH")
A6: 2000 - 2001 | B6: 2000-01-01 | C6: =COUNT(Membership_Snapshots!F2:F1193) | D6: =COUNTIFS(Changes_Log!$B$2:$B$1535,A6,Changes_Log!$E$2:$E$1535,"Added") | E6: =COUNTIFS(Changes_Log!$B$2:$B$1535,A6,Changes_Log!$E$2:$E$1535,"Removed") | F6: =C6+D6-E6 | G6: =IF(F6=C7,"OK","MISMATCH")
A7: 2002 - 2003 | B7: 2002-01-01 | C7: =COUNT(Membership_Snapshots!G2:G1193) | D7: =COUNTIFS(Changes_Log!$B$2:$B$1535,A7,Changes_Log!$E$2:$E$1535,"Added") | E7: =COUNTIFS(Changes_Log!$B$2:$B$1535,A7,Changes_Log!$E$2:$E$1535,"Removed") | F7: =C7+D7-E7 | G7: =IF(F7=C8,"OK","MISMATCH")
A8: 2004 - 2005 | B8: 2004-01-01 | C8: =COUNT(Membership_Snapshots!H2:H1193) | D8: =COUNTIFS(Changes_Log!$B$2:$B$1535,A8,Changes_Log!$E$2:$E$1535,"Added") | E8: =COUNTIFS(Changes_Log!$B$2:$B$1535,A8,Changes_Log!$E$2:$E$1535,"Removed") | F8: =C8+D8-E8 | G8: =IF(F8=C9,"OK","MISMATCH")
A9: 2006 - 2007 | B9: 2006-01-01 | C9: =COUNT(Membership_Snapshots!I2:I1193) | D9: =COUNTIFS(Changes_Log!$B$2:$B$1535,A9,Changes_Log!$E$2:$E$1535,"Added") | E9: =COUNTIFS(Changes_Log!$B$2:$B$1535,A9,Changes_Log!$E$2:$E$1535,"Removed") | F9: =C9+D9-E9 | G9: =IF(F9=C10,"OK","MISMATCH")
A10: 2008 - 2009 | B10: 2008-01-01 | C10: =COUNT(Membership_Snapshots!J2:J1193) | D10: =COUNTIFS(Changes_Log!$B$2:$B$1535,A10,Changes_Log!$E$2:$E$1535,"Added") | E10: =COUNTIFS(Changes_Log!$B$2:$B$1535,A10,Changes_Log!$E$2:$E$1535,"Removed") | F10: =C10+D10-E10 | G10: =IF(F10=C11,"OK","MISMATCH")
A11: 2010 - 2011 | B11: 2010-01-01 | C11: =COUNT(Membership_Snapshots!K2:K1193) | D11: =COUNTIFS(Changes_Log!$B$2:$B$1535,A11,Changes_Log!$E$2:$E$1535,"Added") | E11: =COUNTIFS(Changes_Log!$B$2:$B$1535,A11,Changes_Log!$E$2:$E$1535,"Removed") | F11: =C11+D11-E11 | G11: =IF(F11=C12,"OK","MISMATCH")
A12: 2012 - 2013 | B12: 2012-01-01 | C12: =COUNT(Membership_Snapshots!L2:L1193) | D12: =COUNTIFS(Changes_Log!$B$2:$B$1535,A12,Changes_Log!$E$2:$E$1535,"Added") | E12: =COUNTIFS(Changes_Log!$B$2:$B$1535,A12,Changes_Log!$E$2:$E$1535,"Removed") | F12: =C12+D12-E12 | G12: =IF(F12=C13,"OK","MISMATCH")
A13: 2014 - 2015 | B13: 2014-01-01 | C13: =COUNT(Membership_Snapshots!M2:M1193) | D13: =COUNTIFS(Changes_Log!$B$2:$B$1535,A13,Changes_Log!$E$2:$E$1535,"Added") | E13: =COUNTIFS(Changes_Log!$B$2:$B$1535,A13,Changes_Log!$E$2:$E$1535,"Removed") | F13: =C13+D13-E13 | G13: =IF(F13=C14,"OK","MISMATCH")
A14: 2016 - 2017 | B14: 2016-01-01 | C14: =COUNT(Membership_Snapshots!N2:N1193) | D14: =COUNTIFS(Changes_Log!$B$2:$B$1535,A14,Changes_Log!$E$2:$E$1535,"Added") | E14: =COUNTIFS(Changes_Log!$B$2:$B$1535,A14,Changes_Log!$E$2:$E$1535,"Removed") | F14: =C14+D14-E14 | G14: =IF(F14=C15,"OK","MISMATCH")
A15: 2018 - 2019 | B15: 2018-01-01 | C15: =COUNT(Membership_Snapshots!O2:O1193) | D15: =COUNTIFS(Changes_Log!$B$2:$B$1535,A15,Changes_Log!$E$2:$E$1535,"Added") | E15: =COUNTIFS(Changes_Log!$B$2:$B$1535,A15,Changes_Log!$E$2:$E$1535,"Removed") | F15: =C15+D15-E15 | G15: =IF(F15=C16,"OK","MISMATCH")
A16: 2020 - 2021 | B16: 2020-01-01 | C16: =COUNT(Membership_Snapshots!P2:P1193) | D16: =COUNTIFS(Changes_Log!$B$2:$B$1535,A16,Changes_Log!$E$2:$E$1535,"Added") | E16: =COUNTIFS(Changes_Log!$B$2:$B$1535,A16,Changes_Log!$E$2:$E$1535,"Removed") | F16: =C16+D16-E16 | G16: =IF(F16=C17,"OK","MISMATCH")
A17: 2022 - 2023 | B17: 2022-01-01 | C17: =COUNT(Membership_Snapshots!Q2:Q1193) | D17: =COUNTIFS(Changes_Log!$B$2:$B$1535,A17,Changes_Log!$E$2:$E$1535,"Added") | E17: =COUNTIFS(Changes_Log!$B$2:$B$1535,A17,Changes_Log!$E$2:$E$1535,"Removed") | F17: =C17+D17-E17 | G17: =IF(F17=C18,"OK","MISMATCH")
A18: 2024 - 2025 | B18: 2024-01-01 | C18: =COUNT(Membership_Snapshots!R2:R1193) | D18: =COUNTIFS(Changes_Log!$B$2:$B$1535,A18,Changes_Log!$E$2:$E$1535,"Added") | E18: =COUNTIFS(Changes_Log!$B$2:$B$1535,A18,Changes_Log!$E$2:$E$1535,"Removed") | F18: =C18+D18-E18 | G18: =IF(F18=C19,"OK","MISMATCH")
A19: 2026 - Aug 2026 | B19: 2026-01-01 | C19: =COUNT(Membership_Snapshots!S2:S1193) | D19: =COUNTIFS(Changes_Log!$B$2:$B$1535,A19,Changes_Log!$E$2:$E$1535,"Added") | E19: =COUNTIFS(Changes_Log!$B$2:$B$1535,A19,Changes_Log!$E$2:$E$1535,"Removed") | F19: =C19+D19-E19 | G19: =IF(F19=COUNT(Membership_Snapshots!T2:T1193),"OK","MISMATCH")
A21: Notes
A22: Source: fja05680/sp500 (GitHub) point-in-time S&P 500 constituent lists, 1996-01-02 to 2026-08-18; last snapshot matches the current 503-member list.
A23: Changes_Log is derived by diffing consecutive daily constituent lists: a ticker present in one list but absent from the next is Removed, and the reverse is Added.
A24: The source gives WHO and WHEN, not WHY. The Note column flags same-day add/remove pairs as swaps; these are usually mergers, acquisitions, ticker or name changes, or replacements.
A25: Specific reasons (e.g. Facebook -> Meta) were added by me only for a short list of well-known cases and are not from the source. Verify the rest against S&P Dow Jones Indices press releases.
A26: Tickers are as-listed on the date; reused tickers (e.g. AAL) can refer to different companies over time (see Ticker_Tenure).
A27: Company and sector names are only available for current members (from the source's sp500.csv). Former members show ticker only.
A28: The first period starts at the data's first date (1996-01-02); later periods start Jan 1 of even years, and the final period runs to 2026-08-18.
A29: Membership_Snapshots: 1 = member on that snapshot date.

Sheet Changes_Log
A1: Date | B1: Period (2-yr) | C1: Ticker | D1: Company (current members only) | E1: Action | F1: Note
A2: 1996-01-22 | B2: 1996 - 1997 | C2: CSE | E2: Added | F2: Index swap: same-day add/remove (replacement, merger, acquisition or ticker change - verify)
A3: 1996-01-22 | B3: 1996 - 1997 | C3: BCO | E3: Removed | F3: Index swap: same-day add/remove (replacement, merger, acquisition or ticker change - verify)
A4: 1996-02-12 | B4: 1996 - 1997 | C4: BAY | E4: Added | F4: Index swap: same-day add/remove (replacement, merger, acquisition or ticker change - verify)
A5: 1996-02-12 | B5: 1996 - 1997 | C5: CCB | E5: Removed | F5: Index swap: same-day add/remove (replacement, merger, acquisition or ticker change - verify)
A6: 1996-03-08 | B6: 1996 - 1997 | C6: FITB | D6: Fifth Third Bancorp | E6: Added | F6: Index swap: same-day add/remove (replacement, merger, acquisition or ticker change - verify)
A7: 1996-03-08 | B7: 1996 - 1997 | C7: HDLM | E7: Removed | F7: Index swap: same-day add/remove (replacement, merger, acquisition or ticker change - verify)
A8: 1996-03-13 | B8: 1996 - 1997 | C8: GNT | E8: Added | F8: Index swap: same-day add/remove (replacement, merger, acquisition or ticker change - verify)
A9: 1996-03-13 | B9: 1996 - 1997 | C9: FBO | E9: Removed | F9: Index swap: same-day add/remove (replacement, merger, acquisition or ticker change - verify)
A10: 1996-03-28 | B10: 1996 - 1997 | C10: EMC | E10: Added | F10: Index swap: same-day add/remove (replacement, merger, acquisition or ticker change - verify)
A11: 1996-03-28 | B11: 1996 - 1997 | C11: CYR | E11: Removed | F11: Index swap: same-day add/remove (replacement, merger, acquisition or ticker change - verify)
A12: 1996-04-01 | B12: 1996 - 1997 | C12: NLV | E12: Added | F12: Index swap: same-day add/remove (replacement, merger, acquisition or ticker change - verify)
A13: 1996-04-01 | B13: 1996 - 1997 | C13: WCOEQ | E13: Added | F13: Index swap: same-day add/remove (replacement, merger, acquisition or ticker change - verify)
A14: 1996-04-01 | B14: 1996 - 1997 | C14: CMB | E14: Removed | F14: Index swap: same-day add/remove (replacement, merger, acquisition or ticker change - verify)
A15: 1996-04-01 | B15: 1996 - 1997 | C15: I | E15: Removed | F15: Index swap: same-day add/remove (replacement, merger, acquisition or ticker change - verify)
A16: 1996-04-23 | B16: 1996 - 1997 | C16: AON | D16: Aon plc | E16: Added | F16: Index swap: same-day add/remove (replacement, merger, acquisition or ticker change - verify)
A17: 1996-04-23 | B17: 1996 - 1997 | C17: LOR | E17: Removed | F17: Index swap: same-day add/remove (replacement, merger, acquisition or ticker change - verify)
A18: 1996-05-31 | B18: 1996 - 1997 | C18: TUP | E18: Added | F18: Index swap: same-day add/remove (replacement, merger, acquisition or ticker change - verify)
A19: 1996-05-31 | B19: 1996 - 1997 | C19: PMI | E19: Removed | F19: Index swap: same-day add/remove (replacement, merger, acquisition or ticker change - verify)
A20: 1996-07-19 | B20: 1996 - 1997 | C20: MTG | E20: Added | F20: Index swap: same-day add/remove (replacement, merger, acquisition or ticker change - verify)
A21: 1996-07-19 | B21: 1996 - 1997 | C21: USHC | E21: Removed | F21: Index swap: same-day add/remove (replacement, merger, acquisition or ticker change - verify)
A22: 1996-07-22 | B22: 1996 - 1997 | C22: BMGCA | E22: Added | F22: Index swap: same-day add/remove (replacement, merger, acquisition or ticker change - verify)
A23: 1996-07-22 | B23: 1996 - 1997 | C23: CAL | E23: Removed | F23: Index swap: same-day add/remove (replacement, merger, acquisition or ticker change - verify)
A24: 1996-08-16 | B24: 1996 - 1997 | C24: HFS | E24: Added | F24: Index swap: same-day add/remove (replacement, merger, acquisition or ticker change - verify)
A25: 1996-08-16 | B25: 1996 - 1997 | C25: SEG | E25: Added | F25: Index swap: same-day add/remove (replacement, merger, acquisition or ticker change - verify)
A26: 1996-08-16 | B26: 1996 - 1997 | C26: COV | E26: Removed | F26: Index swap: same-day add/remove (replacement, merger, acquisition or ticker change - verify)
A27: 1996-09-06 | B27: 1996 - 1997 | C27: DELL | D27: Dell Technologies | E27: Added | F27: Index swap: same-day add/remove (replacement, merger, acquisition or ticker change - verify)
A28: 1996-09-06 | B28: 1996 - 1997 | C28: VAT | E28: Removed | F28: Index swap: same-day add/remove (replacement, merger, acquisition or ticker change - verify)
A29: 1996-10-01 | B29: 1996 - 1997 | C29: LU | E29: Added | F29: Index swap: same-day add/remove (replacement, merger, acquisition or ticker change - verify)
A30: 1996-10-01 | B30: 1996 - 1997 | C30: OM | E30: Removed | F30: Index swap: same-day add/remove (replacement, merger, acquisition or ticker change - verify)
A31: 1996-10-16 | B31: 1996 - 1997 | C31: UPR | E31: Added | F31: Index swap: same-day add/remove (replacement, merger, acquisition or ticker change - verify)
A32: 1996-10-16 | B32: 1996 - 1997 | C32: THY | E32: Removed | F32: Index swap: same-day add/remove (replacement, merger, acquisition or ticker change - verify)
A33: 1996-11-04 | B33: 1996 - 1997 | C33: RX | E33: Added | F33: Index swap: same-day add/remove (replacement, merger, acquisition or ticker change - verify)
A34: 1996-11-04 | B34: 1996 - 1997 | C34: YRCW | E34: Removed | F34: Index swap: same-day add/remove (replacement, merger, acquisition or ticker change - verify)
A35: 1996-12-03 | B35: 1996 - 1997 | C35: MBI | E35: Added | F35: Index swap: same-day add/remove (replacement, merger, acquisition or ticker change - verify)
A36: 1996-12-03 | B36: 1996 - 1997 | C36: CNW | E36: Removed | F36: Index swap: same-day add/remove (replacement, merger, acquisition or ticker change - verify)
A37: 1996-12-19 | B37: 1996 - 1997 | C37: GDT | E37: Added | F37: Index swap: same-day add/remove (replacement, merger, acquisition or ticker change - verify)
A38: 1996-12-19 | B38: 1996 - 1997 | C38: BLY | E38: Removed | F38: Index swap: same-day add/remove (replacement, merger, acquisition or ticker change - verify)
A39: 1997-01-02 | B39: 1996 - 1997 | C39: AZO | D39: AutoZone | E39: Added | F39: Index swap: same-day add/remove (replacement, merger, acquisition or ticker change - verify)
A40: 1997-01-02 | B40: 1996 - 1997 | C40: FRO | E40: Added | F40: Index swap: same-day add/remove (replacement, merger, acquisition or ticker change - verify)
A41: 1997-01-02 | B41: 1996 - 1997 | C41: TMO | D41: Thermo Fisher Scientific | E41: Added | F41: Index swap: same-day add/remove (replacement, merger, acquisition or ticker change - verify)
A42: 1997-01-02 | B42: 1996 - 1997 | C42: LUB | E42: Removed | F42: Index swap: same-day add/remove (replacement, merger, acquisition or ticker change - verify)
A43: 1997-01-02 | B43: 1996 - 1997 | C43: RYAN | E43: Removed | F43: Index swap: same-day add/remove (replacement, merger, acquisition or ticker change - verify)
A44: 1997-01-02 | B44: 1996 - 1997 | C44: SHN | E44: Removed | F44: Index swap: same-day add/remove (replacement, merger, acquisition or ticker change - verify)
A45: 1997-01-07 | B45: 1996 - 1997 | C45: BOAT | E45: Removed | F45: Index change (reason not in source)
A46: 1997-01-08 | B46: 1996 - 1997 | C46: EHC | E46: Added | F46: Index change (reason not in source)
A47: 1997-01-15 | B47: 1996 - 1997 | C47: CNC | D47: Centene Corporation | E47: Added | F47: Index swap: same-day add/remove (replacement, merger, acquisition or ticker change - verify)
A48: 1997-01-15 | B48: 1996 - 1997 | C48: AAL | E48: Removed | F48: Index swap: same-day add/remove (replacement, merger, acquisition or ticker change - verify)
A49: 1997-04-01 | B49: 1996 - 1997 | C49: PAC | E49: Removed | F49: Index change (reason not in source)
A50: 1997-04-03 | B50: 1996 - 1997 | C50: PTC | D50: PTC Inc. | E50: Added | F50: Index change (reason not in source)
A51: 1997-05-06 | B51: 1996 - 1997 | C51: ADBE | D51: Adobe Inc. | E51: Added | F51: Index swap: same-day add/remove (replacement, merger, acquisition or ticker change - verify)
A52: 1997-05-06 | B52: 1996 - 1997 | C52: GLD | E52: Removed | F52: Index swap: same-day add/remove (replacement, merger, acquisition or ticker change - verify)
A53: 1997-05-27 | B53: 1996 - 1997 | C53: CAH | D53: Cardinal Health | E53: Added | F53: Index swap: same-day add/remove (replacement, merger, acquisition or ticker change - verify)
A54: 1997-05-27 | B54: 1996 - 1997 | C54: CRR | E54: Removed | F54: Index swap: same-day add/remove (replacement, merger, acquisition or ticker change - verify)
A55: 1997-06-02 | B55: 1996 - 1997 | C55: SCHW | D55: Charles Schwab Corporation | E55: Added | F55: Index swap: same-day add/remove (replacement, merger, acquisition or ticker change - verify)
A56: 1997-06-02 | B56: 1996 - 1997 | C56: DWD | E56: Removed | F56: Index swap: same-day add/remove (replacement, merger, acquisition or ticker change - verify)
A57: 1997-06-18 | B57: 1996 - 1997 | C57: CFC | E57: Added | F57: Index swap: same-day add/remove (replacement, merger, acquisition or ticker change - verify)
A58: 1997-06-18 | B58: 1996 - 1997 | C58: USH | E58: Removed | F58: Index swap: same-day add/remove (replacement, merger, acquisition or ticker change - verify)
A59: 1997-06-19 | B59: 1996 - 1997 | C59: EFX | D59: Equifax | E59: Added | F59: Index swap: same-day add/remove (replacement, merger, acquisition or ticker change - verify)
A60: 1997-06-19 | B60: 1996 - 1997 | C60: PEL | E60: Removed | F60: Index swap: same-day add/remove (replacement, merger, acquisition or ticker change - verify)
A61: 1997-07-02 | B61: 1996 - 1997 | C61: WAMUQ | E61: Added | F61: Index swap: same-day add/remove (replacement, merger, acquisition or ticker change - verify)
A62: 1997-07-02 | B62: 1996 - 1997 | C62: GWF | E62: Removed | F62: Index swap: same-day add/remove (replacement, merger, acquisition or ticker change - verify)
A63: 1997-07-17 | B63: 1996 - 1997 | C63: SAI | E63: Added | F63: Index swap: same-day add/remove (replacement, merger, acquisition or ticker change - verify)
A64: 1997-07-17 | B64: 1996 - 1997 | C64: GIDL | E64: Removed | F64: Index swap: same-day add/remove (replacement, merger, acquisition or ticker change - verify)
A65: 1997-07-28 | B65: 1996 - 1997 | C65: APA | D65: APA Corporation | E65: Added | F65: Index swap: same-day add/remove (replacement, merger, acquisition or ticker change - verify)
A66: 1997-07-28 | B66: 1996 - 1997 | C66: APC | E66: Added | F66: Index swap: same-day add/remove (replacement, merger, acquisition or ticker change - verify)
A67: 1997-07-28 | B67: 1996 - 1997 | C67: INGR | E67: Removed | F67: Index swap: same-day add/remove (replacement, merger, acquisition or ticker change - verify)
A68: 1997-07-28 | B68: 1996 - 1997 | C68: SFS | E68: Removed | F68: Index swap: same-day add/remove (replacement, merger, acquisition or ticker change - verify)
A69: 1997-08-01 | B69: 1996 - 1997 | C69: MD | E69: Removed | F69: Index change (reason not in source)
A70: 1997-08-04 | B70: 1996 - 1997 | C70: OI | E70: Added | F70: Index swap: same-day add/remove (replacement, merger, acquisition or ticker change - verify)
A71: 1997-08-04 | B71: 1996 - 1997 | C71: PGR | D71: Progressive Corporation | E71: Added | F71: Index swap: same-day add/remove (replacement, merger, acquisition or ticker change - verify)
A72: 1997-08-04 | B72: 1996 - 1997 | C72: USBC | E72: Removed | F72: Index swap: same-day add/remove (replacement, merger, acquisition or ticker change - verify)
A73: 1997-08-06 | B73: 1996 - 1997 | C73: HBAN | D73: Huntington Bancshares | E73: Added | F73: Index swap: same-day add/remove (replacement, merger, acquisition or ticker change - verify)
A74: 1997-08-06 | B74: 1996 - 1997 | C74: ENS | E74: Removed | F74: Index swap: same-day add/remove (replacement, merger, acquisition or ticker change - verify)
A75: 1997-08-07 | B75: 1996 - 1997 | C75: MIR | E75: Added | F75: Index swap: same-day add/remove (replacement, merger, acquisition or ticker change - verify)
A76: 1997-08-07 | B76: 1996 - 1997 | C76: NAE | E76: Removed | F76: Index swap: same-day add/remove (replacement, merger, acquisition or ticker change - verify)
A77: 1997-08-15 | B77: 1996 - 1997 | C77: NYN | E77: Removed | F77: Index change (reason not in source)
A78: 1997-08-18 | B78: 1996 - 1997 | C78: STT | D78: State Street Corporation | E78: Added | F78: Index change (reason not in source)
A79: 1997-09-02 | B79: 1996 - 1997 | C79: CCU | E79: Added | F79: Index swap: same-day add/remove (replacement, merger, acquisition or ticker change - verify)
A80: 1997-09-02 | B80: 1996 - 1997 | C80: TDM | E80: Removed | F80: Index swap: same-day add/remove (replacement, merger, acquisition or ticker change - verify)
A81: 1997-09-15 | B81: 1996 - 1997 | C81: KLAC | D81: KLA Corporation | E81: Added | F81: Index swap: same-day add/remove (replacement, merger, acquisition or ticker change - verify)
A82: 1997-09-15 | B82: 1996 - 1997 | C82: AMH | E82: Removed | F82: Index swap: same-day add/remove (replacement, merger, acquisition or ticker change - verify)
A83: 1997-10-07 | B83: 1996 - 1997 | C83: YUM | D83: Yum! Brands | E83: Added | F83: Index swap: same-day add/remove (replacement, merger, acquisition or ticker change - verify)
A84: 1997-10-07 | B84: 1996 - 1997 | C84: SRR | E84: Removed | F84: Index swap: same-day add/remove (replacement, merger, acquisition or ticker change - verify)
A85: 1997-10-23 | B85: 1996 - 1997 | C85: HBOC | E85: Added | F85: Index swap: same-day add/remove (replacement, merger, acquisition or ticker change - verify)
A86: 1997-10-23 | B86: 1996 - 1997 | C86: LLX | E86: Removed | F86: Index swap: same-day add/remove (replacement, merger, acquisition or ticker change - verify)
A87: 1997-11-28 | B87: 1996 - 1997 | C87: SB | E87: Removed | F87: Index change (reason not in source)
A88: 1997-12-01 | B88: 1996 - 1997 | C88: SNV | E88: Added | F88: Index change (reason not in source)
A89: 1997-12-04 | B89: 1996 - 1997 | C89: BBT | E89: Added | F89: Index swap: same-day add/remove (replacement, merger, acquisition or ticker change - verify)
A90: 1997-12-04 | B90: 1996 - 1997 | C90: BEV | E90: Removed | F90: Index swap: same-day add/remove (replacement, merger, acquisition or ticker change - verify)
A91: 1997-12-18 | B91: 1996 - 1997 | C91: CINF | D91: Cincinnati Financial | E91: Added | F91: Index swap: same-day add/remove (replacement, merger, acquisition or ticker change - verify)
A92: 1997-12-18 | B92: 1996 - 1997 | C92: HFS | E92: Removed | F92: Index swap: same-day add/remove (replacement, merger, acquisition or ticker change - verify)
A93: 1997-12-24 | B93: 1996 - 1997 | C93: OMC | D93: Omnicom Group | E93: Added | F93: Index swap: same-day add/remove (replacement, merger, acquisition or ticker change - verify)
A94: 1997-12-24 | B94: 1996 - 1997 | C94: FLMIQ | E94: Removed | F94: Index swap: same-day add/remove (replacement, merger, acquisition or ticker change - verify)
A95: 1998-01-12 | B95: 1998 - 1999 | C95: LEHMQ | E95: Added | F95: Index swap: same-day add/remove (replacement, merger, acquisition or ticker change - verify)
A96: 1998-01-12 | B96: 1998 - 1999 | C96: BBI | E96: Removed | F96: Index swap: same-day add/remove (replacement, merger, acquisition or ticker change - verify)
A97: 1998-01-20 | B97: 1998 - 1999 | C97: BIG | E97: Added | F97: Index swap: same-day add/remove (replacement, merger, acquisition or ticker change - verify)
A98: 1998-01-20 | B98: 1998 - 1999 | C98: ECO | E98: Removed | F98: Index swap: same-day add/remove (replacement, merger, acquisition or ticker change - verify)
A99: 1998-01-28 | B99: 1998 - 1999 | C99: SUB | E99: Added | F99: Index swap: same-day add/remove (replacement, merger, acquisition or ticker change - verify)
A100: 1998-01-28 | B100: 1998 - 1999 | C100: CBB | E100: Removed | F100: Index swap: same-day add/remove (replacement, merger, acquisition or ticker change - verify)
...

Sheet Membership_Snapshots
A1: Ticker | B1: Company (current members only) | C1: Sector (current members only) | D1: 1996-01-02 | E1: 1998-01-01 | F1: 2000-01-01 | G1: 2002-01-01 | H1: 2004-01-01 | I1: 2006-01-01 | J1: 2008-01-01 | K1: 2010-01-01 | L1: 2012-01-01 | M1: 2014-01-01 | N1: 2016-01-01 | O1: 2018-01-01 | P1: 2020-01-01 | Q1: 2022-01-01 | R1: 2024-01-01 | S1: 2026-01-01 | T1: 2026-08-18
A2: A | B2: Agilent Technologies | C2: Health Care | G2: 1 | H2: 1 | I2: 1 | J2: 1 | K2: 1 | L2: 1 | M2: 1 | N2: 1 | O2: 1 | P2: 1 | Q2: 1 | R2: 1 | S2: 1 | T2: 1
A3: AABA | F3: 1 | G3: 1 | H3: 1 | I3: 1 | J3: 1 | K3: 1 | L3: 1 | M3: 1 | N3: 1
A4: AAL | D4: 1 | N4: 1 | O4: 1 | P4: 1 | Q4: 1 | R4: 1
A5: AAMRQ | D5: 1 | E5: 1 | F5: 1 | G5: 1
A6: AAP | N6: 1 | O6: 1 | P6: 1 | Q6: 1
A7: AAPL | B7: Apple Inc. | C7: Information Technology | D7: 1 | E7: 1 | F7: 1 | G7: 1 | H7: 1 | I7: 1 | J7: 1 | K7: 1 | L7: 1 | M7: 1 | N7: 1 | O7: 1 | P7: 1 | Q7: 1 | R7: 1 | S7: 1 | T7: 1
A8: ABBV | B8: AbbVie | C8: Health Care | M8: 1 | N8: 1 | O8: 1 | P8: 1 | Q8: 1 | R8: 1 | S8: 1 | T8: 1
A9: ABC | G9: 1 | H9: 1 | I9: 1 | J9: 1 | K9: 1 | L9: 1 | M9: 1 | N9: 1 | O9: 1 | P9: 1 | Q9: 1
A10: ABI | D10: 1 | E10: 1 | F10: 1 | G10: 1 | H10: 1 | I10: 1 | J10: 1
A11: ABKFQ | G11: 1 | H11: 1 | I11: 1 | J11: 1
A12: ABMD | P12: 1 | Q12: 1
A13: ABNB | B13: Airbnb | C13: Consumer Discretionary | R13: 1 | S13: 1 | T13: 1
A14: ABS | D14: 1 | E14: 1 | F14: 1 | G14: 1 | H14: 1 | I14: 1
A15: ABT | B15: Abbott Laboratories | C15: Health Care | D15: 1 | E15: 1 | F15: 1 | G15: 1 | H15: 1 | I15: 1 | J15: 1 | K15: 1 | L15: 1 | M15: 1 | N15: 1 | O15: 1 | P15: 1 | Q15: 1 | R15: 1 | S15: 1 | T15: 1
A16: ABX | D16: 1 | E16: 1 | F16: 1 | G16: 1
A17: ACAS | J17: 1
A18: ACGL | B18: Arch Capital Group | C18: Financials | R18: 1 | S18: 1 | T18: 1
A19: ACKH | D19: 1 | E19: 1 | F19: 1
A20: ACN | B20: Accenture | C20: Information Technology | L20: 1 | M20: 1 | N20: 1 | O20: 1 | P20: 1 | Q20: 1 | R20: 1 | S20: 1 | T20: 1
A21: ACS | I21: 1 | J21: 1 | K21: 1
A22: ACV | D22: 1 | E22: 1 | F22: 1 | G22: 1 | H22: 1 | I22: 1
A23: ADBE | B23: Adobe Inc. | C23: Information Technology | E23: 1 | F23: 1 | G23: 1 | H23: 1 | I23: 1 | J23: 1 | K23: 1 | L23: 1 | M23: 1 | N23: 1 | O23: 1 | P23: 1 | Q23: 1 | R23: 1 | S23: 1 | T23: 1
A24: ADCT | F24: 1 | G24: 1 | H24: 1 | I24: 1
A25: ADI | B25: Analog Devices | C25: Information Technology | F25: 1 | G25: 1 | H25: 1 | I25: 1 | J25: 1 | K25: 1 | L25: 1 | M25: 1 | N25: 1 | O25: 1 | P25: 1 | Q25: 1 | R25: 1 | S25: 1 | T25: 1
A26: ADM | B26: Archer Daniels Midland | C26: Consumer Staples | D26: 1 | E26: 1 | F26: 1 | G26: 1 | H26: 1 | I26: 1 | J26: 1 | K26: 1 | L26: 1 | M26: 1 | N26: 1 | O26: 1 | P26: 1 | Q26: 1 | R26: 1 | S26: 1 | T26: 1
A27: ADP | B27: Automatic Data Processing | C27: Industrials | D27: 1 | E27: 1 | F27: 1 | G27: 1 | H27: 1 | I27: 1 | J27: 1 | K27: 1 | L27: 1 | M27: 1 | N27: 1 | O27: 1 | P27: 1 | Q27: 1 | R27: 1 | S27: 1 | T27: 1
A28: ADS | M28: 1 | N28: 1 | O28: 1 | P28: 1
A29: ADSK | B29: Autodesk | C29: Information Technology | D29: 1 | E29: 1 | F29: 1 | G29: 1 | H29: 1 | I29: 1 | J29: 1 | K29: 1 | L29: 1 | M29: 1 | N29: 1 | O29: 1 | P29: 1 | Q29: 1 | R29: 1 | S29: 1 | T29: 1
A30: ADT | M30: 1 | N30: 1
A31: AEE | B31: Ameren | C31: Utilities | D31: 1 | E31: 1 | F31: 1 | G31: 1 | H31: 1 | I31: 1 | J31: 1 | K31: 1 | L31: 1 | M31: 1 | N31: 1 | O31: 1 | P31: 1 | Q31: 1 | R31: 1 | S31: 1 | T31: 1
A32: AEP | B32: American Electric Power | C32: Utilities | D32: 1 | E32: 1 | F32: 1 | G32: 1 | H32: 1 | I32: 1 | J32: 1 | K32: 1 | L32: 1 | M32: 1 | N32: 1 | O32: 1 | P32: 1 | Q32: 1 | R32: 1 | S32: 1 | T32: 1
A33: AES | B33: AES Corporation | C33: Utilities | F33: 1 | G33: 1 | H33: 1 | I33: 1 | J33: 1 | K33: 1 | L33: 1 | M33: 1 | N33: 1 | O33: 1 | P33: 1 | Q33: 1 | R33: 1 | S33: 1 | T33: 1
A34: AET | D34: 1 | E34: 1 | F34: 1 | G34: 1 | H34: 1 | I34: 1 | J34: 1 | K34: 1 | L34: 1 | M34: 1 | N34: 1 | O34: 1
A35: AFL | B35: Aflac | C35: Financials | F35: 1 | G35: 1 | H35: 1 | I35: 1 | J35: 1 | K35: 1 | L35: 1 | M35: 1 | N35: 1 | O35: 1 | P35: 1 | Q35: 1 | R35: 1 | S35: 1 | T35: 1
A36: AFS.A | F36: 1
A37: AGC | D37: 1 | E37: 1 | F37: 1
A38: AGN | D38: 1 | E38: 1 | F38: 1 | G38: 1 | H38: 1 | I38: 1 | J38: 1 | K38: 1 | L38: 1 | M38: 1 | N38: 1 | O38: 1 | P38: 1
A39: AHM | D39: 1 | E39: 1
A40: AIG | B40: American International Group | C40: Financials | D40: 1 | E40: 1 | F40: 1 | G40: 1 | H40: 1 | I40: 1 | J40: 1 | K40: 1 | L40: 1 | M40: 1 | N40: 1 | O40: 1 | P40: 1 | Q40: 1 | R40: 1 | S40: 1 | T40: 1
A41: AIT | D41: 1 | E41: 1
A42: AIV | H42: 1 | I42: 1 | J42: 1 | K42: 1 | L42: 1 | M42: 1 | N42: 1 | O42: 1 | P42: 1
A43: AIZ | B43: Assurant | C43: Financials | J43: 1 | K43: 1 | L43: 1 | M43: 1 | N43: 1 | O43: 1 | P43: 1 | Q43: 1 | R43: 1 | S43: 1 | T43: 1
A44: AJG | B44: Arthur J. Gallagher & Co. | C44: Financials | O44: 1 | P44: 1 | Q44: 1 | R44: 1 | S44: 1 | T44: 1
A45: AKAM | B45: Akamai Technologies | C45: Information Technology | J45: 1 | K45: 1 | L45: 1 | M45: 1 | N45: 1 | O45: 1 | P45: 1 | Q45: 1 | R45: 1 | S45: 1 | T45: 1
A46: AKS | K46: 1
A47: AL | D47: 1 | E47: 1 | F47: 1 | G47: 1
A48: ALB | B48: Albemarle Corporation | C48: Materials | O48: 1 | P48: 1 | Q48: 1 | R48: 1 | S48: 1 | T48: 1
A49: ALGN | B49: Align Technology | C49: Health Care | O49: 1 | P49: 1 | Q49: 1 | R49: 1 | S49: 1 | T49: 1
A50: ALK | O50: 1 | P50: 1 | Q50: 1
A51: ALL | B51: Allstate | C51: Financials | D51: 1 | E51: 1 | F51: 1 | G51: 1 | H51: 1 | I51: 1 | J51: 1 | K51: 1 | L51: 1 | M51: 1 | N51: 1 | O51: 1 | P51: 1 | Q51: 1 | R51: 1 | S51: 1 | T51: 1
A52: ALLE | B52: Allegion | C52: Industrials | M52: 1 | N52: 1 | O52: 1 | P52: 1 | Q52: 1 | R52: 1 | S52: 1 | T52: 1
A53: ALTR | G53: 1 | H53: 1 | I53: 1 | J53: 1 | K53: 1 | L53: 1 | M53: 1
A54: ALXN | M54: 1 | N54: 1 | O54: 1 | P54: 1
A55: AM | D55: 1 | E55: 1 | F55: 1 | G55: 1 | H55: 1
A56: AMAT | B56: Applied Materials | C56: Information Technology | D56: 1 | E56: 1 | F56: 1 | G56: 1 | H56: 1 | I56: 1 | J56: 1 | K56: 1 | L56: 1 | M56: 1 | N56: 1 | O56: 1 | P56: 1 | Q56: 1 | R56: 1 | S56: 1 | T56: 1
A57: AMCC | G57: 1 | H57: 1 | I57: 1
A58: AMCR | B58: Amcor | C58: Materials | P58: 1 | Q58: 1 | R58: 1 | S58: 1 | T58: 1
A59: AMD | B59: Advanced Micro Devices | C59: Information Technology | D59: 1 | E59: 1 | F59: 1 | G59: 1 | H59: 1 | I59: 1 | J59: 1 | K59: 1 | L59: 1 | O59: 1 | P59: 1 | Q59: 1 | R59: 1 | S59: 1 | T59: 1
A60: AME | B60: Ametek | C60: Industrials | M60: 1 | N60: 1 | O60: 1 | P60: 1 | Q60: 1 | R60: 1 | S60: 1 | T60: 1
A61: AMG | N61: 1 | O61: 1
A62: AMGN | B62: Amgen | C62: Health Care | D62: 1 | E62: 1 | F62: 1 | G62: 1 | H62: 1 | I62: 1 | J62: 1 | K62: 1 | L62: 1 | M62: 1 | N62: 1 | O62: 1 | P62: 1 | Q62: 1 | R62: 1 | S62: 1 | T62: 1
A63: AMH | D63: 1
A64: AMP | B64: Ameriprise Financial | C64: Financials | D64: 1 | E64: 1 | I64: 1 | J64: 1 | K64: 1 | L64: 1 | M64: 1 | N64: 1 | O64: 1 | P64: 1 | Q64: 1 | R64: 1 | S64: 1 | T64: 1
A65: AMT | B65: American Tower | C65: Real Estate | J65: 1 | K65: 1 | L65: 1 | M65: 1 | N65: 1 | O65: 1 | P65: 1 | Q65: 1 | R65: 1 | S65: 1 | T65: 1
A66: AMZN | B66: Amazon | C66: Consumer Discretionary | I66: 1 | J66: 1 | K66: 1 | L66: 1 | M66: 1 | N66: 1 | O66: 1 | P66: 1 | Q66: 1 | R66: 1 | S66: 1 | T66: 1
A67: AN | D67: 1 | E67: 1 | H67: 1 | I67: 1 | J67: 1 | K67: 1 | L67: 1 | M67: 1 | N67: 1
A68: ANDV | J68: 1 | K68: 1 | L68: 1 | M68: 1 | N68: 1 | O68: 1
A69: ANDW | D69: 1 | E69: 1 | F69: 1 | G69: 1 | H69: 1 | I69: 1
A70: ANET | B70: Arista Networks | C70: Information Technology | P70: 1 | Q70: 1 | R70: 1 | S70: 1 | T70: 1
A71: ANF | J71: 1 | K71: 1 | L71: 1
A72: ANRZQ | L72: 1
A73: ANSS | O73: 1 | P73: 1 | Q73: 1 | R73: 1
A74: ANTM | H74: 1 | I74: 1 | J74: 1 | K74: 1 | L74: 1 | M74: 1 | N74: 1 | O74: 1 | P74: 1 | Q74: 1
A75: ANV | D75: 1 | E75: 1
A76: AON | B76: Aon plc | C76: Financials | E76: 1 | F76: 1 | G76: 1 | H76: 1 | I76: 1 | J76: 1 | K76: 1 | L76: 1 | M76: 1 | N76: 1 | O76: 1 | P76: 1 | Q76: 1 | R76: 1 | S76: 1 | T76: 1
A77: AOS | B77: A. O. Smith | C77: Industrials | O77: 1 | P77: 1 | Q77: 1 | R77: 1 | S77: 1 | T77: 1
A78: APA | B78: APA Corporation | C78: Energy | E78: 1 | F78: 1 | G78: 1 | H78: 1 | I78: 1 | J78: 1 | K78: 1 | L78: 1 | M78: 1 | N78: 1 | O78: 1 | P78: 1 | Q78: 1 | R78: 1 | S78: 1 | T78: 1
A79: APC | E79: 1 | F79: 1 | G79: 1 | H79: 1 | I79: 1 | J79: 1 | K79: 1 | L79: 1 | M79: 1 | N79: 1 | O79: 1
A80: APCC | G80: 1 | H80: 1 | I80: 1
A81: APD | B81: Air Products | C81: Materials | D81: 1 | E81: 1 | F81: 1 | G81: 1 | H81: 1 | I81: 1 | J81: 1 | K81: 1 | L81: 1 | M81: 1 | N81: 1 | O81: 1 | P81: 1 | Q81: 1 | R81: 1 | S81: 1 | T81: 1
A82: APH | B82: Amphenol | C82: Information Technology | K82: 1 | L82: 1 | M82: 1 | N82: 1 | O82: 1 | P82: 1 | Q82: 1 | R82: 1 | S82: 1 | T82: 1
A83: APO | B83: Apollo Global Management | C83: Financials | S83: 1 | T83: 1
A84: APOL | H84: 1 | I84: 1 | J84: 1 | K84: 1 | L84: 1
A85: APP | B85: AppLovin | C85: Communication Services | S85: 1 | T85: 1
A86: APTV | B86: Aptiv | C86: Consumer Discretionary | M86: 1 | N86: 1 | O86: 1 | P86: 1 | Q86: 1 | R86: 1 | S86: 1 | T86: 1
A87: AR | D87: 1 | E87: 1
A88: ARC | D88: 1 | E88: 1 | F88: 1
A89: ARE | B89: Alexandria Real Estate Equities | C89: Real Estate | O89: 1 | P89: 1 | Q89: 1 | R89: 1 | S89: 1 | T89: 1
A90: ARES | B90: Ares Management | C90: Financials | S90: 1 | T90: 1
A91: ARG | K91: 1 | L91: 1 | M91: 1 | N91: 1
A92: ARNC | D92: 1 | E92: 1 | F92: 1 | G92: 1 | H92: 1 | I92: 1 | J92: 1 | K92: 1 | L92: 1 | M92: 1 | N92: 1 | O92: 1 | P92: 1
A93: AS | D93: 1 | E93: 1
A94: ASC | D94: 1 | E94: 1
A95: ASH | D95: 1 | E95: 1 | F95: 1 | G95: 1 | H95: 1 | I95: 1 | J95: 1
A96: ASN | I96: 1
A97: ASO | F97: 1 | G97: 1 | H97: 1 | I97: 1
A98: AT | D98: 1 | E98: 1 | F98: 1 | G98: 1 | H98: 1 | I98: 1
A99: ATGE | K99: 1 | L99: 1
A100: ATI | D100: 1 | E100: 1 | F100: 1 | G100: 1 | H100: 1 | I100: 1 | J100: 1 | K100: 1 | L100: 1 | M100: 1
...

Sheet Ticker_Tenure
A1: Ticker | B1: Company (current members only) | C1: First date in S&P 500 | D1: Last date in S&P 500 (blank = still member) | E1: Status
A2: A | B2: Agilent Technologies | C2: 2000-06-05 | E2: Current
A3: AABA | C3: 1999-12-08 | D3: 2017-06-19 | E3: Former
A4: AAL | C4: 1996-01-02 | D4: 1997-01-15 | E4: Former
A5: AAL | C5: 2015-03-23 | D5: 2024-09-23 | E5: Former
A6: AAMRQ | C6: 1996-01-02 | D6: 2003-03-14 | E6: Former
A7: AAP | C7: 2015-07-09 | D7: 2023-08-25 | E7: Former
A8: AAPL | B8: Apple Inc. | C8: 1996-01-02 | E8: Current
A9: ABBV | B9: AbbVie | C9: 2013-01-02 | E9: Current
A10: ABC | C10: 2001-08-30 | D10: 2023-08-30 | E10: Former
A11: ABI | C11: 1996-01-02 | D11: 2008-11-24 | E11: Former
A12: ABKFQ | C12: 2000-12-11 | D12: 2008-06-11 | E12: Former
A13: ABMD | C13: 2018-05-31 | D13: 2022-12-22 | E13: Former
A14: ABNB | B14: Airbnb | C14: 2023-09-18 | E14: Current
A15: ABS | C15: 1996-01-02 | D15: 2006-06-02 | E15: Former
A16: ABT | B16: Abbott Laboratories | C16: 1996-01-02 | E16: Current
A17: ABX | C17: 1996-01-02 | D17: 2002-07-22 | E17: Former
A18: ACAS | C18: 2007-07-09 | D18: 2009-03-04 | E18: Former
A19: ACGL | B19: Arch Capital Group | C19: 2022-11-01 | E19: Current
A20: ACKH | C20: 1996-01-02 | D20: 2000-11-17 | E20: Former
A21: ACN | B21: Accenture | C21: 2011-07-06 | E21: Current
A22: ACS | C22: 2004-04-02 | D22: 2010-02-08 | E22: Former
A23: ACV | C23: 1996-01-02 | D23: 2006-11-17 | E23: Former
A24: ADBE | B24: Adobe Inc. | C24: 1997-05-06 | E24: Current
A25: ADCT | C25: 1999-08-02 | D25: 2007-07-02 | E25: Former
A26: ADI | B26: Analog Devices | C26: 1999-10-12 | E26: Current
A27: ADM | B27: Archer Daniels Midland | C27: 1996-01-02 | E27: Current
A28: ADP | B28: Automatic Data Processing | C28: 1996-01-02 | E28: Current
A29: ADS | C29: 2013-12-23 | D29: 2020-06-22 | E29: Former
A30: ADSK | B30: Autodesk | C30: 1996-01-02 | E30: Current
A31: ADT | C31: 2012-10-02 | D31: 2016-05-02 | E31: Former
A32: AEE | B32: Ameren | C32: 1996-01-02 | E32: Current
A33: AEP | B33: American Electric Power | C33: 1996-01-02 | E33: Current
A34: AES | B34: AES Corporation | C34: 1998-10-02 | E34: Current
A35: AET | C35: 1996-01-02 | D35: 2018-11-29 | E35: Former
A36: AFL | B36: Aflac | C36: 1999-05-28 | E36: Current
A37: AFS.A | C37: 1998-04-08 | D37: 2000-12-01 | E37: Former
A38: AGC | C38: 1996-01-02 | D38: 2001-08-29 | E38: Former
A39: AGN | C39: 1996-01-02 | D39: 2020-05-12 | E39: Former
A40: AHM | C40: 1996-01-02 | D40: 1998-10-01 | E40: Former
A41: AIG | B41: American International Group | C41: 1996-01-02 | E41: Current
A42: AIT | C42: 1996-01-02 | D42: 1999-10-11 | E42: Former
A43: AIV | C43: 2003-03-14 | D43: 2020-12-21 | E43: Former
A44: AIZ | B44: Assurant | C44: 2007-04-10 | E44: Current
A45: AJG | B45: Arthur J. Gallagher & Co. | C45: 2016-05-31 | E45: Current
A46: AKAM | B46: Akamai Technologies | C46: 2007-07-12 | E46: Current
A47: AKS | C47: 2008-07-01 | D47: 2011-12-19 | E47: Former
A48: AL | C48: 1996-01-02 | D48: 2002-07-22 | E48: Former
A49: ALB | B49: Albemarle Corporation | C49: 2016-07-01 | E49: Current
A50: ALGN | B50: Align Technology | C50: 2017-06-19 | E50: Current
A51: ALK | C51: 2016-05-13 | D51: 2023-12-18 | E51: Former
A52: ALL | B52: Allstate | C52: 1996-01-02 | E52: Current
A53: ALLE | B53: Allegion | C53: 2013-12-02 | E53: Current
A54: ALTR | C54: 2000-04-18 | D54: 2015-12-28 | E54: Former
A55: ALXN | C55: 2012-05-25 | D55: 2021-07-21 | E55: Former
A56: AM | C56: 1996-01-02 | D56: 2004-05-03 | E56: Former
A57: AMAT | B57: Applied Materials | C57: 1996-01-02 | E57: Current
A58: AMCC | C58: 2001-01-02 | D58: 2006-05-18 | E58: Former
A59: AMCR | B59: Amcor | C59: 2019-06-07 | E59: Current
A60: AMD | B60: Advanced Micro Devices | C60: 1996-01-02 | D60: 2013-09-23 | E60: Former
A61: AMD | B61: Advanced Micro Devices | C61: 2017-03-20 | E61: Current
A62: AME | B62: Ametek | C62: 2013-09-23 | E62: Current
A63: AMG | C63: 2014-07-01 | D63: 2019-12-23 | E63: Former
A64: AMGN | B64: Amgen | C64: 1996-01-02 | E64: Current
A65: AMH | C65: 1996-01-02 | D65: 1997-09-15 | E65: Former
A66: AMP | B66: Ameriprise Financial | C66: 1996-01-02 | D66: 1999-04-05 | E66: Former
A67: AMP | B67: Ameriprise Financial | C67: 2005-10-03 | E67: Current
A68: AMT | B68: American Tower | C68: 2007-11-19 | E68: Current
A69: AMTM | C69: 2024-09-30 | D69: 2024-12-23 | E69: Former
A70: AMZN | B70: Amazon | C70: 2005-11-21 | E70: Current
A71: AN | C71: 1996-01-02 | D71: 1999-01-04 | E71: Former
A72: AN | C72: 2003-02-24 | D72: 2017-08-08 | E72: Former
A73: ANDV | C73: 2007-09-27 | D73: 2018-10-01 | E73: Former
A74: ANDW | C74: 1996-01-02 | D74: 2006-10-02 | E74: Former
A75: ANET | B75: Arista Networks | C75: 2018-08-28 | E75: Current
A76: ANF | C76: 2007-03-29 | D76: 2013-12-23 | E76: Former
A77: ANRZQ | C77: 2011-06-02 | D77: 2012-10-02 | E77: Former
A78: ANSS | C78: 2017-06-19 | D78: 2025-07-18 | E78: Former
A79: ANTM | C79: 2002-07-25 | D79: 2022-06-28 | E79: Former
A80: ANV | C80: 1996-01-02 | D80: 1999-04-12 | E80: Former
A81: AON | B81: Aon plc | C81: 1996-04-23 | E81: Current
A82: AOS | B82: A. O. Smith | C82: 2017-07-26 | E82: Current
A83: APA | B83: APA Corporation | C83: 1997-07-28 | E83: Current
A84: APC | C84: 1997-07-28 | D84: 2019-08-09 | E84: Former
A85: APCC | C85: 2000-06-01 | D85: 2007-02-15 | E85: Former
A86: APD | B86: Air Products | C86: 1996-01-02 | E86: Current
A87: APH | B87: Amphenol | C87: 2008-09-30 | E87: Current
A88: APO | B88: Apollo Global Management | C88: 2024-12-23 | E88: Current
A89: APOL | C89: 2002-05-15 | D89: 2013-07-01 | E89: Former
A90: APP | B90: AppLovin | C90: 2025-09-22 | E90: Current
A91: APTV | B91: Aptiv | C91: 2012-12-24 | E91: Current
A92: AR | C92: 1996-01-02 | D92: 1999-10-27 | E92: Former
A93: ARC | C93: 1996-01-02 | D93: 2000-04-18 | E93: Former
A94: ARE | B94: Alexandria Real Estate Equities | C94: 2017-03-20 | E94: Current
A95: ARES | B95: Ares Management | C95: 2025-12-11 | E95: Current
A96: ARG | C96: 2009-09-09 | D96: 2016-05-23 | E96: Former
A97: ARNC | C97: 1996-01-02 | D97: 2020-04-06 | E97: Former
A98: AS | C98: 1996-01-02 | D98: 1998-11-24 | E98: Former
A99: ASC | C99: 1996-01-02 | D99: 1999-06-24 | E99: Former
A100: ASH | C100: 1996-01-02 | D100: 2008-11-14 | E100: Former
...
